AudioUtils/__init__.py
AudioUtils/main.py
AudioUtils/setup.py
AudioUtils/test.py
CallSummarisation/__init__.py
CallSummarisation/main.py
CallSummarisation/setup.py
CallSummarisation/test.py
DummyPackage/__init__.py
DummyPackage/main.py
DummyPackage/setup.py
DummyPackage/test.py
S3_Related/__init__.py
S3_Related/main.py
S3_Related/setup.py
S3_Related/test.py
SnowFlake_Related/__init__.py
SnowFlake_Related/main.py
SnowFlake_Related/setup.py
SnowFlake_Related/test.py
SpeakerClassification/__init__.py
SpeakerClassification/main.py
SpeakerClassification/setup.py
SpeakerClassification/test.py
TextUtils/__init__.py
TextUtils/main.py
TextUtils/setup.py
TextUtils/test.py
ZipFile_Related/__init__.py
ZipFile_Related/main.py
ZipFile_Related/setup.py
ZipFile_Related/test.py
SpeakerClassification-0.0.1.dist-info/METADATA
SpeakerClassification-0.0.1.dist-info/WHEEL
SpeakerClassification-0.0.1.dist-info/top_level.txt
SpeakerClassification-0.0.1.dist-info/RECORD
