Metadata-Version: 2.1
Name: SpeakerClassification
Version: 0.0.1
Requires-Dist: numpy
Requires-Dist: pandas
Requires-Dist: scikit-learn
Requires-Dist: nltk
Requires-Dist: boto3
